pycircos/__init__.py
pycircos-1.0.2.dist-info/LICENSE
pycircos-1.0.2.dist-info/METADATA
pycircos-1.0.2.dist-info/WHEEL
pycircos-1.0.2.dist-info/top_level.txt
pycircos-1.0.2.dist-info/RECORD
