Metadata-Version: 2.1
Name: pycircos
Version: 1.0.2
Summary: This Tools is Design for NGS Circos Plot with using Python.
Home-page: https://github.com/KimBioInfoStudio/PyCircos
Author: Yunfei Wang, Baochen Yang
Author-email: yfwang0405@gmail.com, yangbaochen1217@gmail.com
License: AGPLv3
Keywords: Python NGS Circos Plot
Platform: UNKNOWN
Classifier: Environment :: Console
Classifier: Development Status :: 3 - Alpha
Classifier: Intended Audience :: Developers
Classifier: License :: Free for non-commercial use
Classifier: License :: OSI Approved :: GNU General Public License (GPL)
Classifier: Operating System :: Unix
Classifier: Operating System :: POSIX :: Linux
Classifier: Operating System :: Microsoft :: Windows
Classifier: Programming Language :: Python :: 3
Classifier: Programming Language :: Python :: 3.5
Classifier: Programming Language :: Python :: 3.6
Classifier: Programming Language :: Python :: 3.7
Classifier: Topic :: Scientific/Engineering :: Bio-Informatics
Requires-Python: >=3.5
